[
    {
        "content": "<p>fitzgen opened <a href=\"https://github.com/bytecodealliance/wasmtime/pull/12676\">PR #12676</a> from <code>fitzgen:try-clone-and-try-to-owned-in-prelude</code> to <code>bytecodealliance:main</code>:</p>\n<blockquote>\n<p>The non-<code>Try</code> versions are both in <code>std</code>'s prelude, so it makes sense to add them to our prelude.</p>\n<p>&lt;!--<br>\nPlease make sure you include the following information:</p>\n<ul>\n<li>\n<p>If this work has been discussed elsewhere, please include a link to that<br>\n  conversation. If it was discussed in an issue, just mention \"issue #...\".</p>\n</li>\n<li>\n<p>Explain why this change is needed. If the details are in an issue already,<br>\n  this can be brief.</p>\n</li>\n</ul>\n<p>Our development process is documented in the Wasmtime book:<br>\n<a href=\"https://docs.wasmtime.dev/contributing-development-process.html\">https://docs.wasmtime.dev/contributing-development-process.html</a></p>\n<p>Please ensure all communication follows the code of conduct:<br>\n<a href=\"https://github.com/bytecodealliance/wasmtime/blob/main/CODE_OF_CONDUCT.md\">https://github.com/bytecodealliance/wasmtime/blob/main/CODE_OF_CONDUCT.md</a><br>\n--&gt;</p>\n</blockquote>",
        "id": 575880786,
        "sender_full_name": "Wasmtime GitHub notifications bot",
        "timestamp": 1772057374
    },
    {
        "content": "<p>fitzgen requested <a href=\"https://github.com/cfallin\">cfallin</a> for a review on <a href=\"https://github.com/bytecodealliance/wasmtime/pull/12676\">PR #12676</a>.</p>",
        "id": 575880788,
        "sender_full_name": "Wasmtime GitHub notifications bot",
        "timestamp": 1772057374
    },
    {
        "content": "<p>fitzgen requested <a href=\"https://github.com/orgs/bytecodealliance/teams/wasmtime-core-reviewers\">wasmtime-core-reviewers</a> for a review on <a href=\"https://github.com/bytecodealliance/wasmtime/pull/12676\">PR #12676</a>.</p>",
        "id": 575880789,
        "sender_full_name": "Wasmtime GitHub notifications bot",
        "timestamp": 1772057374
    },
    {
        "content": "<p>alexcrichton submitted <a href=\"https://github.com/bytecodealliance/wasmtime/pull/12676#pullrequestreview-3857279855\">PR review</a>.</p>",
        "id": 575881255,
        "sender_full_name": "Wasmtime GitHub notifications bot",
        "timestamp": 1772057549
    },
    {
        "content": "<p>fitzgen updated <a href=\"https://github.com/bytecodealliance/wasmtime/pull/12676\">PR #12676</a>.</p>",
        "id": 575883691,
        "sender_full_name": "Wasmtime GitHub notifications bot",
        "timestamp": 1772058475
    },
    {
        "content": "<p>fitzgen has enabled auto merge for <a href=\"https://github.com/bytecodealliance/wasmtime/pull/12676\">PR #12676</a>.</p>",
        "id": 575883708,
        "sender_full_name": "Wasmtime GitHub notifications bot",
        "timestamp": 1772058484
    },
    {
        "content": "<p>fitzgen updated <a href=\"https://github.com/bytecodealliance/wasmtime/pull/12676\">PR #12676</a>.</p>",
        "id": 575891741,
        "sender_full_name": "Wasmtime GitHub notifications bot",
        "timestamp": 1772061390
    },
    {
        "content": "<p>fitzgen updated <a href=\"https://github.com/bytecodealliance/wasmtime/pull/12676\">PR #12676</a>.</p>",
        "id": 575895821,
        "sender_full_name": "Wasmtime GitHub notifications bot",
        "timestamp": 1772063293
    },
    {
        "content": "<p>fitzgen added <a href=\"https://github.com/bytecodealliance/wasmtime/pull/12676\">PR #12676 Add <code>TryClone</code> and <code>TryToOwned</code> to our prelude</a> to the merge queue.</p>",
        "id": 575897541,
        "sender_full_name": "Wasmtime GitHub notifications bot",
        "timestamp": 1772064091
    },
    {
        "content": "<p>fitzgen merged <a href=\"https://github.com/bytecodealliance/wasmtime/pull/12676\">PR #12676</a>.</p>",
        "id": 575900312,
        "sender_full_name": "Wasmtime GitHub notifications bot",
        "timestamp": 1772065564
    },
    {
        "content": "<p>fitzgen removed <a href=\"https://github.com/bytecodealliance/wasmtime/pull/12676\">PR #12676 Add <code>TryClone</code> and <code>TryToOwned</code> to our prelude</a> from the merge queue.</p>",
        "id": 575900313,
        "sender_full_name": "Wasmtime GitHub notifications bot",
        "timestamp": 1772065564
    }
]