[
    {
        "content": "<p>fitzgen requested <a href=\"https://github.com/cfallin\">cfallin</a> for a review on <a href=\"https://github.com/bytecodealliance/wasmtime/pull/13741\">PR #13741</a>.</p>",
        "id": 606790637,
        "sender_full_name": "Wasmtime GitHub notifications bot",
        "timestamp": 1782499654
    },
    {
        "content": "<p>fitzgen opened <a href=\"https://github.com/bytecodealliance/wasmtime/pull/13741\">PR #13741</a> from <code>fitzgen:avoid-last-stores-clone</code> to <code>bytecodealliance:main</code>:</p>\n<blockquote>\n<p>The <code>LastStores</code> struct contains an owned heap allocation (via <code>SecondaryMap</code>) so best to avoid cloning it when we can.</p>\n<p>&lt;!--<br>\nPlease make sure you include the following information:</p>\n<ul>\n<li>\n<p>If this work has been discussed elsewhere, please include a link to that<br>\n  conversation. If it was discussed in an issue, just mention \"issue #...\".</p>\n</li>\n<li>\n<p>Explain why this change is needed. If the details are in an issue already,<br>\n  this can be brief.</p>\n</li>\n</ul>\n<p>Our development process is documented in the Wasmtime book:<br>\n<a href=\"https://docs.wasmtime.dev/contributing-development-process.html\">https://docs.wasmtime.dev/contributing-development-process.html</a></p>\n<p>Please ensure all communication follows the code of conduct:<br>\n<a href=\"https://github.com/bytecodealliance/wasmtime/blob/main/CODE_OF_CONDUCT.md\">https://github.com/bytecodealliance/wasmtime/blob/main/CODE_OF_CONDUCT.md</a><br>\n--&gt;</p>\n</blockquote>",
        "id": 606790638,
        "sender_full_name": "Wasmtime GitHub notifications bot",
        "timestamp": 1782499654
    },
    {
        "content": "<p>fitzgen requested <a href=\"https://github.com/orgs/bytecodealliance/teams/wasmtime-compiler-reviewers\">wasmtime-compiler-reviewers</a> for a review on <a href=\"https://github.com/bytecodealliance/wasmtime/pull/13741\">PR #13741</a>.</p>",
        "id": 606790639,
        "sender_full_name": "Wasmtime GitHub notifications bot",
        "timestamp": 1782499654
    },
    {
        "content": "<p><span aria-label=\"thumbs up\" class=\"emoji emoji-1f44d\" role=\"img\" title=\"thumbs up\">:thumbs_up:</span> cfallin submitted <a href=\"https://github.com/bytecodealliance/wasmtime/pull/13741#pullrequestreview-4582193252\">PR review</a>:</p>\n<blockquote>\n<p>Good find, thanks!</p>\n</blockquote>",
        "id": 606797574,
        "sender_full_name": "Wasmtime GitHub notifications bot",
        "timestamp": 1782502249
    },
    {
        "content": "<p>fitzgen has enabled auto merge for <a href=\"https://github.com/bytecodealliance/wasmtime/pull/13741\">PR #13741</a>.</p>",
        "id": 606810611,
        "sender_full_name": "Wasmtime GitHub notifications bot",
        "timestamp": 1782508038
    },
    {
        "content": "<p>fitzgen updated <a href=\"https://github.com/bytecodealliance/wasmtime/pull/13741\">PR #13741</a>.</p>",
        "id": 606810636,
        "sender_full_name": "Wasmtime GitHub notifications bot",
        "timestamp": 1782508046
    },
    {
        "content": "<p>github-actions[bot] added the label <code>cranelift</code> on <a href=\"https://github.com/bytecodealliance/wasmtime/pull/13741\">PR #13741</a>.</p>",
        "id": 606816875,
        "sender_full_name": "Wasmtime GitHub notifications bot",
        "timestamp": 1782511513
    },
    {
        "content": "<p>fitzgen updated <a href=\"https://github.com/bytecodealliance/wasmtime/pull/13741\">PR #13741</a>.</p>",
        "id": 607190913,
        "sender_full_name": "Wasmtime GitHub notifications bot",
        "timestamp": 1782750609
    },
    {
        "content": "<p>fitzgen updated <a href=\"https://github.com/bytecodealliance/wasmtime/pull/13741\">PR #13741</a>.</p>",
        "id": 607224726,
        "sender_full_name": "Wasmtime GitHub notifications bot",
        "timestamp": 1782761551
    },
    {
        "content": "<p>fitzgen added <a href=\"https://github.com/bytecodealliance/wasmtime/pull/13741\">PR #13741 Cranelift: Avoid a clone of <code>LastStores</code> in the alias analysis</a> to the merge queue.</p>",
        "id": 607226335,
        "sender_full_name": "Wasmtime GitHub notifications bot",
        "timestamp": 1782762167
    },
    {
        "content": "<p><span aria-label=\"check\" class=\"emoji emoji-2705\" role=\"img\" title=\"check\">:check:</span> fitzgen merged <a href=\"https://github.com/bytecodealliance/wasmtime/pull/13741\">PR #13741</a>.</p>",
        "id": 607230649,
        "sender_full_name": "Wasmtime GitHub notifications bot",
        "timestamp": 1782763635
    },
    {
        "content": "<p>fitzgen removed <a href=\"https://github.com/bytecodealliance/wasmtime/pull/13741\">PR #13741 Cranelift: Avoid a clone of <code>LastStores</code> in the alias analysis</a> from the merge queue.</p>",
        "id": 607230652,
        "sender_full_name": "Wasmtime GitHub notifications bot",
        "timestamp": 1782763635
    }
]