[
    {
        "content": "<p>fitzgen opened <a href=\"https://github.com/bytecodealliance/wasmtime/pull/13679\">PR #13679</a> from <code>fitzgen:release-46-inline-copy-alias-region-backport</code> to <code>bytecodealliance:release-46.0.0</code>:</p>\n<blockquote>\n<p>Backport of #13610 to the 46.x release branch.</p>\n</blockquote>",
        "id": 604253699,
        "sender_full_name": "Wasmtime GitHub notifications bot",
        "timestamp": 1781721757
    },
    {
        "content": "<p>fitzgen requested <a href=\"https://github.com/cfallin\">cfallin</a> for a review on <a href=\"https://github.com/bytecodealliance/wasmtime/pull/13679\">PR #13679</a>.</p>",
        "id": 604253707,
        "sender_full_name": "Wasmtime GitHub notifications bot",
        "timestamp": 1781721757
    },
    {
        "content": "<p>fitzgen requested <a href=\"https://github.com/orgs/bytecodealliance/teams/wasmtime-compiler-reviewers\">wasmtime-compiler-reviewers</a> for a review on <a href=\"https://github.com/bytecodealliance/wasmtime/pull/13679\">PR #13679</a>.</p>",
        "id": 604253709,
        "sender_full_name": "Wasmtime GitHub notifications bot",
        "timestamp": 1781721758
    },
    {
        "content": "<p>fitzgen requested <a href=\"https://github.com/orgs/bytecodealliance/teams/wasmtime-core-reviewers\">wasmtime-core-reviewers</a> for a review on <a href=\"https://github.com/bytecodealliance/wasmtime/pull/13679\">PR #13679</a>.</p>",
        "id": 604253714,
        "sender_full_name": "Wasmtime GitHub notifications bot",
        "timestamp": 1781721758
    },
    {
        "content": "<p><span aria-label=\"thumbs up\" class=\"emoji emoji-1f44d\" role=\"img\" title=\"thumbs up\">:thumbs_up:</span> alexcrichton submitted <a href=\"https://github.com/bytecodealliance/wasmtime/pull/13679#pullrequestreview-4518641677\">PR review</a>.</p>",
        "id": 604253966,
        "sender_full_name": "Wasmtime GitHub notifications bot",
        "timestamp": 1781721817
    },
    {
        "content": "<p>alexcrichton has enabled auto merge for <a href=\"https://github.com/bytecodealliance/wasmtime/pull/13679\">PR #13679</a>.</p>",
        "id": 604254000,
        "sender_full_name": "Wasmtime GitHub notifications bot",
        "timestamp": 1781721823
    },
    {
        "content": "<p><span aria-label=\"check\" class=\"emoji emoji-2705\" role=\"img\" title=\"check\">:check:</span> alexcrichton merged <a href=\"https://github.com/bytecodealliance/wasmtime/pull/13679\">PR #13679</a>.</p>",
        "id": 604260613,
        "sender_full_name": "Wasmtime GitHub notifications bot",
        "timestamp": 1781723292
    }
]