[
    {
        "content": "<p>fitzgen opened <a href=\"https://github.com/bytecodealliance/wasmtime/pull/12298\">PR #12298</a> from <code>fitzgen:no-anyhow-macro-in-wasmtime-prelude</code> to <code>bytecodealliance:main</code>:</p>\n<blockquote>\n<p>We are trying to move to <code>format_err!</code> instead.</p>\n<p>Buids on <a href=\"https://github.com/bytecodealliance/wasmtime/pull/12297\">https://github.com/bytecodealliance/wasmtime/pull/12297</a></p>\n</blockquote>",
        "id": 567043067,
        "sender_full_name": "Wasmtime GitHub notifications bot",
        "timestamp": 1767910932
    },
    {
        "content": "<p><strong>fitzgen</strong> requested <a href=\"https://github.com/orgs/bytecodealliance/teams/wasmtime-compiler-reviewers\">wasmtime-compiler-reviewers</a> for a review on <a href=\"https://github.com/bytecodealliance/wasmtime/pull/12298\">PR #12298</a>.</p>",
        "id": 567043069,
        "sender_full_name": "Wasmtime GitHub notifications bot",
        "timestamp": 1767910933
    },
    {
        "content": "<p><strong>fitzgen</strong> requested <a href=\"https://github.com/alexcrichton\">alexcrichton</a> for a review on <a href=\"https://github.com/bytecodealliance/wasmtime/pull/12298\">PR #12298</a>.</p>",
        "id": 567043071,
        "sender_full_name": "Wasmtime GitHub notifications bot",
        "timestamp": 1767910933
    },
    {
        "content": "<p><strong>fitzgen</strong> requested <a href=\"https://github.com/orgs/bytecodealliance/teams/wasmtime-wasi-reviewers\">wasmtime-wasi-reviewers</a> for a review on <a href=\"https://github.com/bytecodealliance/wasmtime/pull/12298\">PR #12298</a>.</p>",
        "id": 567043072,
        "sender_full_name": "Wasmtime GitHub notifications bot",
        "timestamp": 1767910933
    },
    {
        "content": "<p><strong>fitzgen</strong> requested <a href=\"https://github.com/orgs/bytecodealliance/teams/wasmtime-core-reviewers\">wasmtime-core-reviewers</a> for a review on <a href=\"https://github.com/bytecodealliance/wasmtime/pull/12298\">PR #12298</a>.</p>",
        "id": 567043074,
        "sender_full_name": "Wasmtime GitHub notifications bot",
        "timestamp": 1767910934
    },
    {
        "content": "<p><strong>fitzgen</strong> requested <a href=\"https://github.com/orgs/bytecodealliance/teams/wasmtime-default-reviewers\">wasmtime-default-reviewers</a> for a review on <a href=\"https://github.com/bytecodealliance/wasmtime/pull/12298\">PR #12298</a>.</p>",
        "id": 567043075,
        "sender_full_name": "Wasmtime GitHub notifications bot",
        "timestamp": 1767910934
    },
    {
        "content": "<p>alexcrichton submitted <a href=\"https://github.com/bytecodealliance/wasmtime/pull/12298#pullrequestreview-3641983429\">PR review</a>.</p>",
        "id": 567059016,
        "sender_full_name": "Wasmtime GitHub notifications bot",
        "timestamp": 1767921915
    },
    {
        "content": "<p>fitzgen updated <a href=\"https://github.com/bytecodealliance/wasmtime/pull/12298\">PR #12298</a>.</p>",
        "id": 567245481,
        "sender_full_name": "Wasmtime GitHub notifications bot",
        "timestamp": 1767985844
    },
    {
        "content": "<p>fitzgen has enabled auto merge for <a href=\"https://github.com/bytecodealliance/wasmtime/pull/12298\">PR #12298</a>.</p>",
        "id": 567245508,
        "sender_full_name": "Wasmtime GitHub notifications bot",
        "timestamp": 1767985853
    },
    {
        "content": "<p>fitzgen merged <a href=\"https://github.com/bytecodealliance/wasmtime/pull/12298\">PR #12298</a>.</p>",
        "id": 567255149,
        "sender_full_name": "Wasmtime GitHub notifications bot",
        "timestamp": 1767989502
    }
]