[
    {
        "content": "<p>posborne edited <a href=\"https://github.com/bytecodealliance/wasmtime/pull/10321\">PR #10321</a>.</p>",
        "id": 503574993,
        "sender_full_name": "Wasmtime GitHub notifications bot",
        "timestamp": 1741193768
    },
    {
        "content": "<p>posborne updated <a href=\"https://github.com/bytecodealliance/wasmtime/pull/10321\">PR #10321</a>.</p>",
        "id": 503846310,
        "sender_full_name": "Wasmtime GitHub notifications bot",
        "timestamp": 1741280968
    },
    {
        "content": "<p>alexcrichton merged <a href=\"https://github.com/bytecodealliance/wasmtime/pull/10321\">PR #10321</a>.</p>",
        "id": 503864319,
        "sender_full_name": "Wasmtime GitHub notifications bot",
        "timestamp": 1741286283
    }
]